cay/__init__.py
cay/cli.py
cay/main.py
cay-0.1.5.dist-info/entry_points.txt
cay-0.1.5.dist-info/LICENSE
cay-0.1.5.dist-info/WHEEL
cay-0.1.5.dist-info/METADATA
cay-0.1.5.dist-info/RECORD
